{
  "name": "xsloader.js",
  "version": "1.1.0",
  "description": "xsloader is a JavaScript file and module loader like requirejs but not requirejs",
  "main": "dist/xsloader.js",
  "scripts": {
    "test": "echo \"Error: no test specified\" && exit 1",
    "build:dev": "set NODE_ENV=development && rollup -c  scripts/rollup.config.js",
    "build:release": "set NODE_ENV=production && rollup -c  scripts/rollup.config.js",
    "build:all": "npm run build:dev && npm run build:release"
  },
  "keywords": [
    "js loader",
    "require",
    "define"
  ],
  "author": "gzxishan",
  "license": "Apache-2.0",
  "homepage": "https://github.com/gzxishan/xsloader#readme",
  "devDependencies": {
    "@babel/cli": "^7.4.5",
    "@babel/core": "^7.4.5",
    "@babel/plugin-proposal-class-properties": "^7.4.5",
    "@babel/plugin-proposal-export-default-from": "^7.4.5",
    "@babel/plugin-proposal-object-rest-spread": "^7.4.5",
    "@babel/preset-env": "^7.4.5",
    "babel-eslint": "^8.2.6",
    "rollup": "^1.14.2",
    "rollup-plugin-babel": "^4.3.2",
    "rollup-plugin-eslint": "^6.0.0",
    "rollup-plugin-node-resolve": "^5.0.1",
    "rollup-plugin-uglify": "^6.0.2"
  },
  "dependencies": {
    "@babel/polyfill": "^7.4.4"
  }
}
